MANIFEST.in
README.md
setup.cfg
setup.py
hvac/__init__.py
hvac/exceptions.py
hvac/version
hvac/tests/__init__.py
hvac/tests/test_integration.py
hvac/tests/util.py
hvac/v1/__init__.py
klarrio_hvac.egg-info/PKG-INFO
klarrio_hvac.egg-info/SOURCES.txt
klarrio_hvac.egg-info/dependency_links.txt
klarrio_hvac.egg-info/requires.txt
klarrio_hvac.egg-info/top_level.txt