Metadata-Version: 2.1
Name: klarrio-hvac
Version: 0.5.0
Summary: HashiCorp Vault API client
Home-page: https://github.com/ianunruh/hvac
Author: Ian Unruh
Author-email: ianunruh@gmail.com
License: UNKNOWN
Keywords: hashicorp,vault
Platform: UNKNOWN
Classifier: License :: OSI Approved :: Apache Software License
Provides-Extra: parser
